init_thumbnail/__init__.py
init_thumbnail/__main__.py
init_thumbnail/main.py
init_thumbnail-0.1.2.dist-info/METADATA
init_thumbnail-0.1.2.dist-info/WHEEL
init_thumbnail-0.1.2.dist-info/entry_points.txt
init_thumbnail-0.1.2.dist-info/RECORD
