Metadata-Version: 2.1
Name: init-thumbnail
Version: 0.1.2
Summary: Package for creating youtube thumbnail
Author: vaibhavblayer
Author-email: vaibhavblayer@gmail.com
Requires-Python: >=3.11,<4.0
Classifier: Programming Language :: Python :: 3
Classifier: Programming Language :: Python :: 3.11
